odoo/addons/brand/README.rst
odoo/addons/brand/__init__.py
odoo/addons/brand/__manifest__.py
odoo/addons/brand/i18n/brand.pot
odoo/addons/brand/models/__init__.py
odoo/addons/brand/models/res_brand.py
odoo/addons/brand/models/res_brand_mixin.py
odoo/addons/brand/models/res_company.py
odoo/addons/brand/models/res_config_settings.py
odoo/addons/brand/readme/CONTRIBUTORS.rst
odoo/addons/brand/readme/CREDITS.rst
odoo/addons/brand/readme/DESCRIPTION.rst
odoo/addons/brand/readme/USAGE.rst
odoo/addons/brand/security/res_brand.xml
odoo/addons/brand/static/description/icon.png
odoo/addons/brand/static/description/index.html
odoo/addons/brand/views/res_brand.xml
odoo/addons/brand/views/res_config_settings.xml
odoo13_addon_brand-13.0.1.0.2.dist-info/METADATA
odoo13_addon_brand-13.0.1.0.2.dist-info/WHEEL
odoo13_addon_brand-13.0.1.0.2.dist-info/top_level.txt
odoo13_addon_brand-13.0.1.0.2.dist-info/RECORD
