Metadata-Version: 2.1
Name: odoo13-addon-brand
Version: 13.0.1.0.2
Summary: This is a base addon for brand modules. It adds the brand object and its menu and define an abstract model to be inherited from branded objects
Home-page: https://github.com/OCA/brand
Author: Odoo Community Association (OCA),ACSONE SA/NV
Author-email: support@odoo-community.org
License: AGPL-3
Platform: UNKNOWN
Classifier: Programming Language :: Python
Classifier: Framework :: Odoo
Classifier: Framework :: Odoo :: 13.0
Classifier: License :: OSI Approved :: GNU Affero General Public License v3
Requires-Python: >=3.5
Requires-Dist: odoo (<13.1dev,>=13.0a)
